[{"DATA":"2025-01-01","Visao":"M\u00e9dico-Hospitalar","Modalidade":"Filantropia","Porte":"Pequeno","Contraprestacoes_Efetivas":131981349.9600000083,"Eventos_Indenizaveis":96685530.3599999994},{"DATA":"2025-01-01","Visao":"M\u00e9dico-Hospitalar","Modalidade":"Autogest\u00e3o","Porte":"M\u00e9dio","Contraprestacoes_Efetivas":2492199011.6499996185,"Eventos_Indenizaveis":2388382221.8600001335},{"DATA":"2025-01-01","Visao":"M\u00e9dico-Hospitalar","Modalidade":"Autogest\u00e3o","Porte":"Grande","Contraprestacoes_Efetivas":4035440748.4399995804,"Eventos_Indenizaveis":3678074214.1400003433},{"DATA":"2025-01-01","Visao":"M\u00e9dico-Hospitalar","Modalidade":"Seguradora Especializada em Sa\u00fade","Porte":"Grande","Contraprestacoes_Efetivas":20074564719.4599990845,"Eventos_Indenizaveis":15301466112.0399990082},{"DATA":"2025-04-01","Visao":"M\u00e9dico-Hospitalar","Modalidade":"Medicina de Grupo","Porte":"Pequeno","Contraprestacoes_Efetivas":1008014687.4600000381,"Eventos_Indenizaveis":776276014.4000000954},{"DATA":"2025-04-01","Visao":"M\u00e9dico-Hospitalar","Modalidade":"Filantropia","Porte":"M\u00e9dio","Contraprestacoes_Efetivas":561316615.3700000048,"Eventos_Indenizaveis":457789101.9599999785},{"DATA":"2025-04-01","Visao":"M\u00e9dico-Hospitalar","Modalidade":"Cooperativa M\u00e9dica","Porte":"M\u00e9dio","Contraprestacoes_Efetivas":6219664337.1300001144,"Eventos_Indenizaveis":5044257859.8700008392},{"DATA":"2025-04-01","Visao":"M\u00e9dico-Hospitalar","Modalidade":"Cooperativa M\u00e9dica","Porte":"Grande","Contraprestacoes_Efetivas":19637325604.5699996948,"Eventos_Indenizaveis":16361524801.6999969482},{"DATA":"2025-04-01","Visao":"M\u00e9dico-Hospitalar","Modalidade":"Seguradora Especializada em Sa\u00fade","Porte":"Pequeno","Contraprestacoes_Efetivas":54748372.950000003,"Eventos_Indenizaveis":89908486.5},{"DATA":"2025-07-01","Visao":"M\u00e9dico-Hospitalar","Modalidade":"Medicina de Grupo","Porte":"Grande","Contraprestacoes_Efetivas":22131164019.8199958801,"Eventos_Indenizaveis":17101737298.2699985504},{"DATA":"2025-07-01","Visao":"M\u00e9dico-Hospitalar","Modalidade":"Autogest\u00e3o","Porte":"M\u00e9dio","Contraprestacoes_Efetivas":2764762483.5400004387,"Eventos_Indenizaveis":2602295790.6300001144},{"DATA":"2025-07-01","Visao":"M\u00e9dico-Hospitalar","Modalidade":"Autogest\u00e3o","Porte":"Grande","Contraprestacoes_Efetivas":5237651497.6000003815,"Eventos_Indenizaveis":4553093881.9600000381},{"DATA":"2025-07-01","Visao":"M\u00e9dico-Hospitalar","Modalidade":"Medicina de Grupo","Porte":"M\u00e9dio","Contraprestacoes_Efetivas":2954536675.6600003242,"Eventos_Indenizaveis":2321193012.5999999046},{"DATA":"2025-07-01","Visao":"M\u00e9dico-Hospitalar","Modalidade":"Seguradora Especializada em Sa\u00fade","Porte":"Pequeno","Contraprestacoes_Efetivas":51036933.3999999985,"Eventos_Indenizaveis":88131055.2699999958},{"DATA":"2025-10-01","Visao":"M\u00e9dico-Hospitalar","Modalidade":"Autogest\u00e3o","Porte":"M\u00e9dio","Contraprestacoes_Efetivas":2738089824.7699999809,"Eventos_Indenizaveis":2726677556.6599998474},{"DATA":"2025-10-01","Visao":"M\u00e9dico-Hospitalar","Modalidade":"Autogest\u00e3o","Porte":"Grande","Contraprestacoes_Efetivas":5219171934.5400009155,"Eventos_Indenizaveis":4748462065.1599998474},{"DATA":"2025-10-01","Visao":"M\u00e9dico-Hospitalar","Modalidade":"Cooperativa M\u00e9dica","Porte":"M\u00e9dio","Contraprestacoes_Efetivas":6489485597.5900020599,"Eventos_Indenizaveis":5221861209.6099996567},{"DATA":"2025-10-01","Visao":"M\u00e9dico-Hospitalar","Modalidade":"Filantropia","Porte":"Pequeno","Contraprestacoes_Efetivas":145501324.3500000238,"Eventos_Indenizaveis":114566538.3600000143},{"DATA":"2025-10-01","Visao":"M\u00e9dico-Hospitalar","Modalidade":"Cooperativa M\u00e9dica","Porte":"Grande","Contraprestacoes_Efetivas":19195890534.9099998474,"Eventos_Indenizaveis":16056207666.6199989319},{"DATA":"2025-04-01","Visao":"M\u00e9dico-Hospitalar","Modalidade":"Medicina de Grupo","Porte":"Sem Informa\u00e7\u00e3o","Contraprestacoes_Efetivas":4272480.1599999992,"Eventos_Indenizaveis":2785110.3699999996},{"DATA":"2025-01-01","Visao":"Exclusivamente Odontol\u00f3gico","Modalidade":"Odontologia de Grupo","Porte":"Pequeno","Contraprestacoes_Efetivas":2575947.46,"Eventos_Indenizaveis":1161910.52},{"DATA":"2025-04-01","Visao":"M\u00e9dico-Hospitalar","Modalidade":"Filantropia","Porte":"Grande","Contraprestacoes_Efetivas":432624024.4199999571,"Eventos_Indenizaveis":341359532.1800000072},{"DATA":"2025-01-01","Visao":"M\u00e9dico-Hospitalar","Modalidade":"Medicina de Grupo","Porte":"Pequeno","Contraprestacoes_Efetivas":975200527.1100003719,"Eventos_Indenizaveis":730336396.4099999666},{"DATA":"2025-01-01","Visao":"M\u00e9dico-Hospitalar","Modalidade":"Cooperativa M\u00e9dica","Porte":"M\u00e9dio","Contraprestacoes_Efetivas":6088869529.7400007248,"Eventos_Indenizaveis":4736999308.7399997711},{"DATA":"2025-01-01","Visao":"M\u00e9dico-Hospitalar","Modalidade":"Cooperativa M\u00e9dica","Porte":"Grande","Contraprestacoes_Efetivas":19308020949.5299987793,"Eventos_Indenizaveis":15221941508.1100006104},{"DATA":"2025-04-01","Visao":"M\u00e9dico-Hospitalar","Modalidade":"Autogest\u00e3o","Porte":"M\u00e9dio","Contraprestacoes_Efetivas":2606298733.4299993515,"Eventos_Indenizaveis":2510004907.9300003052},{"DATA":"2025-04-01","Visao":"Exclusivamente Odontol\u00f3gico","Modalidade":"Odontologia de Grupo","Porte":"Pequeno","Contraprestacoes_Efetivas":2542703.5100000002,"Eventos_Indenizaveis":1188005.26},{"DATA":"2025-07-01","Visao":"M\u00e9dico-Hospitalar","Modalidade":"Cooperativa M\u00e9dica","Porte":"Grande","Contraprestacoes_Efetivas":20017774302.6899986267,"Eventos_Indenizaveis":17193620887.4200019836},{"DATA":"2025-07-01","Visao":"M\u00e9dico-Hospitalar","Modalidade":"Cooperativa M\u00e9dica","Porte":"M\u00e9dio","Contraprestacoes_Efetivas":6327888333.0399999619,"Eventos_Indenizaveis":5243068113.2399997711},{"DATA":"2025-07-01","Visao":"Exclusivamente Odontol\u00f3gico","Modalidade":"Odontologia de Grupo","Porte":"M\u00e9dio","Contraprestacoes_Efetivas":54806664.5600000024,"Eventos_Indenizaveis":15474253.620000001},{"DATA":"2025-07-01","Visao":"Exclusivamente Odontol\u00f3gico","Modalidade":"Odontologia de Grupo","Porte":"Grande","Contraprestacoes_Efetivas":830122340.5400000811,"Eventos_Indenizaveis":313452476.8499999642},{"DATA":"2025-10-01","Visao":"M\u00e9dico-Hospitalar","Modalidade":"Medicina de Grupo","Porte":"M\u00e9dio","Contraprestacoes_Efetivas":3140412000.9299998283,"Eventos_Indenizaveis":2445050189.0900001526},{"DATA":"2025-10-01","Visao":"M\u00e9dico-Hospitalar","Modalidade":"Medicina de Grupo","Porte":"Grande","Contraprestacoes_Efetivas":22865492057.1900024414,"Eventos_Indenizaveis":17456681279.1299972534},{"DATA":"2025-10-01","Visao":"Exclusivamente Odontol\u00f3gico","Modalidade":"Odontologia de Grupo","Porte":"M\u00e9dio","Contraprestacoes_Efetivas":62506019.1000000015,"Eventos_Indenizaveis":18860953.2299999967},{"DATA":"2025-10-01","Visao":"M\u00e9dico-Hospitalar","Modalidade":"Seguradora Especializada em Sa\u00fade","Porte":"Grande","Contraprestacoes_Efetivas":22336057406.7099990845,"Eventos_Indenizaveis":18073289077.3000030518},{"DATA":"2025-10-01","Visao":"Exclusivamente Odontol\u00f3gico","Modalidade":"Odontologia de Grupo","Porte":"Grande","Contraprestacoes_Efetivas":851990841.8099998236,"Eventos_Indenizaveis":327441879.3900001049},{"DATA":"2025-04-01","Visao":"M\u00e9dico-Hospitalar","Modalidade":"Autogest\u00e3o","Porte":"Grande","Contraprestacoes_Efetivas":4715113293.3699998856,"Eventos_Indenizaveis":4223760470.8499999046},{"DATA":"2025-07-01","Visao":"M\u00e9dico-Hospitalar","Modalidade":"Filantropia","Porte":"Pequeno","Contraprestacoes_Efetivas":140155883.7100000083,"Eventos_Indenizaveis":114519659.4800000042},{"DATA":"2025-01-01","Visao":"M\u00e9dico-Hospitalar","Modalidade":"Medicina de Grupo","Porte":"Sem Informa\u00e7\u00e3o","Contraprestacoes_Efetivas":4937990.1200000001,"Eventos_Indenizaveis":335240.73},{"DATA":"2025-01-01","Visao":"M\u00e9dico-Hospitalar","Modalidade":"Cooperativa M\u00e9dica","Porte":"Pequeno","Contraprestacoes_Efetivas":1445596083.1199998856,"Eventos_Indenizaveis":1089369886.5599999428},{"DATA":"2025-01-01","Visao":"M\u00e9dico-Hospitalar","Modalidade":"Medicina de Grupo","Porte":"M\u00e9dio","Contraprestacoes_Efetivas":2635788722.6700000763,"Eventos_Indenizaveis":1992072880.9300000668},{"DATA":"2025-01-01","Visao":"M\u00e9dico-Hospitalar","Modalidade":"Medicina de Grupo","Porte":"Grande","Contraprestacoes_Efetivas":20935712466.0499992371,"Eventos_Indenizaveis":15262442908.4400024414},{"DATA":"2025-04-01","Visao":"Exclusivamente Odontol\u00f3gico","Modalidade":"Odontologia de Grupo","Porte":"M\u00e9dio","Contraprestacoes_Efetivas":55798708.599999994,"Eventos_Indenizaveis":14775140.2100000009},{"DATA":"2025-04-01","Visao":"M\u00e9dico-Hospitalar","Modalidade":"Autogest\u00e3o","Porte":"Pequeno","Contraprestacoes_Efetivas":1223444193.5299999714,"Eventos_Indenizaveis":1034423878.379999876},{"DATA":"2025-04-01","Visao":"Exclusivamente Odontol\u00f3gico","Modalidade":"Odontologia de Grupo","Porte":"Grande","Contraprestacoes_Efetivas":827226142.1899998188,"Eventos_Indenizaveis":278498890.9300000072},{"DATA":"2025-07-01","Visao":"M\u00e9dico-Hospitalar","Modalidade":"Cooperativa M\u00e9dica","Porte":"Pequeno","Contraprestacoes_Efetivas":1527543355.0599999428,"Eventos_Indenizaveis":1290389036.6900000572},{"DATA":"2025-07-01","Visao":"M\u00e9dico-Hospitalar","Modalidade":"Filantropia","Porte":"M\u00e9dio","Contraprestacoes_Efetivas":513931632.6000000238,"Eventos_Indenizaveis":437398015.8700000048},{"DATA":"2025-07-01","Visao":"Exclusivamente Odontol\u00f3gico","Modalidade":"Odontologia de Grupo","Porte":"Pequeno","Contraprestacoes_Efetivas":2589138.6400000001,"Eventos_Indenizaveis":1294885.52},{"DATA":"2025-07-01","Visao":"M\u00e9dico-Hospitalar","Modalidade":"Filantropia","Porte":"Grande","Contraprestacoes_Efetivas":430840281.9199999571,"Eventos_Indenizaveis":368130587.6600000262},{"DATA":"2025-10-01","Visao":"M\u00e9dico-Hospitalar","Modalidade":"Medicina de Grupo","Porte":"Pequeno","Contraprestacoes_Efetivas":1025839171.4299998283,"Eventos_Indenizaveis":779488012.2400001287},{"DATA":"2025-10-01","Visao":"Exclusivamente Odontol\u00f3gico","Modalidade":"Odontologia de Grupo","Porte":"Pequeno","Contraprestacoes_Efetivas":127666069.9099999964,"Eventos_Indenizaveis":46421374.7100000009},{"DATA":"2025-10-01","Visao":"M\u00e9dico-Hospitalar","Modalidade":"Seguradora Especializada em Sa\u00fade","Porte":"Pequeno","Contraprestacoes_Efetivas":54678967.7599999979,"Eventos_Indenizaveis":100544468.0799999684},{"DATA":"2025-10-01","Visao":"M\u00e9dico-Hospitalar","Modalidade":"Medicina de Grupo","Porte":"Sem Informa\u00e7\u00e3o","Contraprestacoes_Efetivas":5405119.1499999994,"Eventos_Indenizaveis":3246983.8199999994},{"DATA":"2025-10-01","Visao":"Exclusivamente Odontol\u00f3gico","Modalidade":"Odontologia de Grupo","Porte":"Sem Informa\u00e7\u00e3o","Contraprestacoes_Efetivas":858761.8600000001,"Eventos_Indenizaveis":365095.04},{"DATA":"2025-01-01","Visao":"Exclusivamente Odontol\u00f3gico","Modalidade":"Odontologia de Grupo","Porte":"Grande","Contraprestacoes_Efetivas":822933052.9500000477,"Eventos_Indenizaveis":264143242.8700000048},{"DATA":"2025-01-01","Visao":"M\u00e9dico-Hospitalar","Modalidade":"Autogest\u00e3o","Porte":"Pequeno","Contraprestacoes_Efetivas":1171776678.6400001049,"Eventos_Indenizaveis":993797938.0500003099},{"DATA":"2025-01-01","Visao":"Exclusivamente Odontol\u00f3gico","Modalidade":"Odontologia de Grupo","Porte":"M\u00e9dio","Contraprestacoes_Efetivas":52892933.25,"Eventos_Indenizaveis":13467332.3300000019},{"DATA":"2025-01-01","Visao":"M\u00e9dico-Hospitalar","Modalidade":"Filantropia","Porte":"M\u00e9dio","Contraprestacoes_Efetivas":547420521.3899999857,"Eventos_Indenizaveis":406552460.7300000191},{"DATA":"2025-04-01","Visao":"M\u00e9dico-Hospitalar","Modalidade":"Medicina de Grupo","Porte":"M\u00e9dio","Contraprestacoes_Efetivas":2865714791.5,"Eventos_Indenizaveis":2171685446.25},{"DATA":"2025-04-01","Visao":"M\u00e9dico-Hospitalar","Modalidade":"Cooperativa M\u00e9dica","Porte":"Pequeno","Contraprestacoes_Efetivas":1496459940.3399999142,"Eventos_Indenizaveis":1150116163.8000001907},{"DATA":"2025-04-01","Visao":"M\u00e9dico-Hospitalar","Modalidade":"Filantropia","Porte":"Pequeno","Contraprestacoes_Efetivas":135048822.849999994,"Eventos_Indenizaveis":106993108.6400000006},{"DATA":"2025-04-01","Visao":"M\u00e9dico-Hospitalar","Modalidade":"Medicina de Grupo","Porte":"Grande","Contraprestacoes_Efetivas":21480432106.8700027466,"Eventos_Indenizaveis":17390700973.9799995422},{"DATA":"2025-07-01","Visao":"M\u00e9dico-Hospitalar","Modalidade":"Autogest\u00e3o","Porte":"Pequeno","Contraprestacoes_Efetivas":1245704314.9300000668,"Eventos_Indenizaveis":1110469031.5700001717},{"DATA":"2025-07-01","Visao":"M\u00e9dico-Hospitalar","Modalidade":"Medicina de Grupo","Porte":"Pequeno","Contraprestacoes_Efetivas":1046040556.6099998951,"Eventos_Indenizaveis":818859582.1699999571},{"DATA":"2025-07-01","Visao":"M\u00e9dico-Hospitalar","Modalidade":"Seguradora Especializada em Sa\u00fade","Porte":"Grande","Contraprestacoes_Efetivas":22143330422.9899978638,"Eventos_Indenizaveis":17814053061.469997406},{"DATA":"2025-10-01","Visao":"M\u00e9dico-Hospitalar","Modalidade":"Autogest\u00e3o","Porte":"Pequeno","Contraprestacoes_Efetivas":1288251514.4700000286,"Eventos_Indenizaveis":1107015517.6199998856},{"DATA":"2025-10-01","Visao":"M\u00e9dico-Hospitalar","Modalidade":"Cooperativa M\u00e9dica","Porte":"Pequeno","Contraprestacoes_Efetivas":1743243770.1500000954,"Eventos_Indenizaveis":1274389388.7199995518},{"DATA":"2025-10-01","Visao":"M\u00e9dico-Hospitalar","Modalidade":"Filantropia","Porte":"M\u00e9dio","Contraprestacoes_Efetivas":609427972.1700000763,"Eventos_Indenizaveis":492590981.1200000048},{"DATA":"2025-04-01","Visao":"M\u00e9dico-Hospitalar","Modalidade":"Cooperativa M\u00e9dica","Porte":"Sem Informa\u00e7\u00e3o","Contraprestacoes_Efetivas":0.0,"Eventos_Indenizaveis":43905275.4099999964},{"DATA":"2025-01-01","Visao":"M\u00e9dico-Hospitalar","Modalidade":"Seguradora Especializada em Sa\u00fade","Porte":"Pequeno","Contraprestacoes_Efetivas":40710092.25,"Eventos_Indenizaveis":89376981.3299999982},{"DATA":"2025-04-01","Visao":"M\u00e9dico-Hospitalar","Modalidade":"Seguradora Especializada em Sa\u00fade","Porte":"Grande","Contraprestacoes_Efetivas":21080409411.6000022888,"Eventos_Indenizaveis":16561585774.5900001526},{"DATA":"2025-10-01","Visao":"M\u00e9dico-Hospitalar","Modalidade":"Filantropia","Porte":"Grande","Contraprestacoes_Efetivas":434091063.5099999905,"Eventos_Indenizaveis":353671846.2900000215},{"DATA":"2025-07-01","Visao":"M\u00e9dico-Hospitalar","Modalidade":"Medicina de Grupo","Porte":"Sem Informa\u00e7\u00e3o","Contraprestacoes_Efetivas":4543608.2100000009,"Eventos_Indenizaveis":3070664.9700000007},{"DATA":"2025-01-01","Visao":"M\u00e9dico-Hospitalar","Modalidade":"Filantropia","Porte":"Grande","Contraprestacoes_Efetivas":429424239.2300000191,"Eventos_Indenizaveis":326593885.3100000024}]